calculadora/__init__.py
calculadora/calculos.py
antonio-1.0.0.dist-info/LICENCE.txt
antonio-1.0.0.dist-info/METADATA
antonio-1.0.0.dist-info/WHEEL
antonio-1.0.0.dist-info/top_level.txt
antonio-1.0.0.dist-info/RECORD
